sherlock/__init__.py
sherlock/__main__.py
sherlock/argument_parser.py
sherlock/future_session.py
sherlock/notify.py
sherlock/result.py
sherlock/sherlock.py
sherlock/sites.py
sherlock/utils.py
sherlock_hunt-0.16.0.dist-info/LICENSE
sherlock_hunt-0.16.0.dist-info/METADATA
sherlock_hunt-0.16.0.dist-info/WHEEL
sherlock_hunt-0.16.0.dist-info/entry_points.txt
sherlock_hunt-0.16.0.dist-info/top_level.txt
sherlock_hunt-0.16.0.dist-info/RECORD
