Metadata-Version: 2.1
Name: sherlock-hunt
Version: 0.16.0
Summary: Sherlock: Find Usernames Across Social Networks
Home-page: https://github.com/mazulo/sherlock
Download-URL: https://github.com/mazulo/sherlock/tarball/0.16.0
Author: Patrick Mazulo
Author-email: pmazulo@gmail.com
License: MIT License
Keywords: cli,code,search,social media
Platform: POSIX
Classifier: License :: OSI Approved :: MIT License
Classifier: Operating System :: OS Independent
Classifier: Development Status :: 5 - Production/Stable
Classifier: Environment :: Console
Classifier: Programming Language :: Python :: 3
Classifier: Programming Language :: Python :: 3.6
Classifier: Programming Language :: Python :: 3.7
Classifier: Programming Language :: Python :: 3.8
Classifier: Programming Language :: Python :: 3.9
Classifier: Programming Language :: Python :: 3.10
Classifier: Topic :: Utilities
License-File: LICENSE
Requires-Dist: certifi (>=2019.6.16)
Requires-Dist: colorama (>=0.4.1)
Requires-Dist: PySocks (>=1.7.0)
Requires-Dist: requests (>=2.28.1)
Requires-Dist: requests-futures (>=1.0.0)
Requires-Dist: stem (>=1.8.0)
Requires-Dist: torrequest (>=0.1.0)
Requires-Dist: pandas (>=1.0.0)
Requires-Dist: openpyxl (<=3.0.10)
